[
  {
    "line": 1,
    "elements": [
      {
        "start_timestamp": "2020-06-09T01:39:20.527Z",
        "before": [
          {
            "result": {
              "duration": 997600,
              "status": "passed"
            },
            "match": {
              "location": "com.zerobank.stepdefnitions.Hooks.setUp()"
            }
          }
        ],
        "line": 3,
        "name": "Add\ta\tnew\tpayee",
        "description": "",
        "id": "add-new-payee-under-pay-bills;add-a-new-payee",
        "after": [
          {
            "result": {
              "duration": 594123000,
              "status": "passed"
            },
            "match": {
              "location": "com.zerobank.stepdefnitions.Hooks.tearDown(io.cucumber.java.Scenario)"
            }
          }
        ],
        "type": "scenario",
        "keyword": "Scenario",
        "steps": [
          {
            "result": {
              "duration": 8929207000,
              "status": "passed"
            },
            "line": 4,
            "name": "Add New Payee tab",
            "match": {
              "location": "com.zerobank.stepdefnitions.AddNewPayee.add_New_Payee_tab()"
            },
            "keyword": "Given "
          },
          {
            "result": {
              "duration": 1919771700,
              "status": "passed"
            },
            "line": 5,
            "name": "creates\tnew\tpayee\tusing following\tinformation",
            "match": {
              "location": "com.zerobank.stepdefnitions.AddNewPayee.creates_new_payee_using_following_information(io.cucumber.datatable.DataTable)"
            },
            "rows": [
              {
                "cells": [
                  "Payee Name",
                  "The Law Offices of Hyde, Price \u0026 Scharks"
                ]
              },
              {
                "cells": [
                  "Payee Address",
                  "100 Same st, Anytown, USA, 10001"
                ]
              },
              {
                "cells": [
                  "Account",
                  "Checking"
                ]
              },
              {
                "cells": [
                  "Payee Details",
                  "XYZ account"
                ]
              }
            ],
            "keyword": "And "
          },
          {
            "result": {
              "duration": 41884500,
              "status": "passed"
            },
            "line": 10,
            "name": "message \"The new payee The Law Offices of Hyde, Price \u0026 Scharks was successfully created.\" should\tbe\tdisplayed",
            "match": {
              "arguments": [
                {
                  "val": "\"The new payee The Law Offices of Hyde, Price \u0026 Scharks was successfully created.\"",
                  "offset": 8
                }
              ],
              "location": "com.zerobank.stepdefnitions.AddNewPayee.messageShouldBeDisplayed(java.lang.String)"
            },
            "keyword": "Then "
          }
        ],
        "tags": [
          {
            "name": "@www"
          }
        ]
      }
    ],
    "name": "Add\tnew\tpayee\tunder\tpay\tbills",
    "description": "",
    "id": "add-new-payee-under-pay-bills",
    "keyword": "Feature",
    "uri": "file:src/test/resources/features/AddNewPayee.feature",
    "tags": []
  }
]